README.rst
setup.py
GitGitlab.egg-info/PKG-INFO
GitGitlab.egg-info/SOURCES.txt
GitGitlab.egg-info/dependency_links.txt
GitGitlab.egg-info/entry_points.txt
GitGitlab.egg-info/requires.txt
GitGitlab.egg-info/top_level.txt
gitgitlab/__init__.py
gitgitlab/auth.py
gitgitlab/cli.py
gitgitlab/client.py
gitgitlab.egg-info/SOURCES.txt