Metadata-Version: 1.0
Name: GitGitlab
Version: 1.1
Summary: gitlab for git
Home-page: UNKNOWN
Author: UNKNOWN
Author-email: UNKNOWN
License: UNKNOWN
Platform: UNKNOWN
